understory/auth/__init__.py
understory/auth/client/__init__.py
understory/auth/client/templates/__init__.py
understory/auth/client/templates/guests.html
understory/auth/client/templates/signin.html
understory/auth/client/templates/signout.html
understory/auth/server/__init__.py
understory/auth/server/templates/__init__.py
understory/auth/server/templates/authorizations.html
understory/auth/server/templates/client.html
understory/auth/server/templates/clients.html
understory/auth/server/templates/consent.html
understory/auth/server/templates/root.html
understory/auth/server/templates/unauthorized.html
understory/auth/util.py
understory_auth-0.0.40.dist-info/LICENSE
understory_auth-0.0.40.dist-info/WHEEL
understory_auth-0.0.40.dist-info/METADATA
understory_auth-0.0.40.dist-info/RECORD
